{
  "title": "Checklista – El, magnetism och induktion",
  "subject": "Fysik",
  "area": "El, magnetism och induktion",
  "intro": "Här kan du träna på vad du behöver kunna om elektricitet, magnetism, elektromagnetism, induktion och Ohms lag.",
  "sections": [
    {
      "title": "1. Elektricitetens grunder",
      "items": [
        "Jag vet vad en atom består av: atomkärna och elektroner.",
        "Jag vet att elektronen är negativt laddad och att atomkärnan är positivt laddad.",
        "Jag vet att elektrisk ström är elektroner som rör sig i en ledning.",
        "Jag vet att spänning är det som pressar fram elektronerna i ledningen.",
        "Jag kan enheten för spänning: volt (V).",
        "Jag kan enheten för strömstyrka: ampere (A).",
        "Jag vet skillnaden mellan likström och växelström.",
        "Jag vet att batterier ger likström.",
        "Jag vet att vägguttag ger växelström."
      ]
    },
    {
      "title": "2. Ledare, isolatorer och resistans",
      "items": [
        "Jag vet att metaller är goda ledare av elektrisk ström.",
        "Jag kan ge exempel på isolatorer, till exempel plast, gummi, glas eller porslin.",
        "Jag vet att resistans betyder motstånd mot elektrisk ström.",
        "Jag kan enheten för resistans: ohm (Ω).",
        "Jag vet att en kort, tjock ledare av koppar leder ström bra.",
        "Jag vet att resistansen ökar om en ledare är lång eller tunn.",
        "Jag vet att resistansen ökar när en ledare blir varm.",
        "Jag vet vad en resistor (motstånd) används till i en krets.",
        "Jag vet vad supraledning betyder på enkel nivå."
      ]
    },
    {
      "title": "3. Elektriska kopplingar",
      "items": [
        "Jag kan känna igen en sluten krets och en öppen krets.",
        "Jag vet vad en kortslutning är på enkel nivå.",
        "Jag kan förklara skillnaden mellan seriekoppling och parallellkoppling.",
        "Jag vet vad som händer med lampor i en seriekoppling om en lampa går sönder.",
        "Jag vet vad som händer med lampor i en parallellkoppling om en lampa går sönder.",
        "Jag vet varför lampor ofta lyser starkare i parallellkoppling än i seriekoppling.",
        "Jag vet vad man vinner på att seriekoppla batterier.",
        "Jag vet vad man vinner på att parallellkoppla batterier.",
        "Jag kan tolka enkla kopplingsscheman."
      ]
    },
    {
      "title": "4. Elsäkerhet",
      "items": [
        "Jag vet att elolyckor kan orsaka både brand och personskador.",
        "Jag kan förklara varför ledningar kan bli farligt varma om strömmen blir för hög.",
        "Jag vet vad en säkring har för uppgift.",
        "Jag vet vad en automatsäkring gör.",
        "Jag vet vad en jordfelsbrytare gör.",
        "Jag vet vad skyddsjordning är på enkel nivå.",
        "Jag vet att elektriska apparater nära vatten kan vara farliga.",
        "Jag vet varför man inte ska överbelasta eluttag och grenkontakter.",
        "Jag vet vad CE-märkning betyder på enkel nivå."
      ]
    },
    {
      "title": "5. Magneter och magnetfält",
      "items": [
        "Jag vet att en magnet har en nordpol och en sydpol.",
        "Jag vet att olika magnetpoler dras mot varandra.",
        "Jag vet att lika magnetpoler stöter bort varandra.",
        "Jag vet att magnetfältet är starkast vid magnetens ändar.",
        "Jag vet att magnetfältets riktning brukar ritas från nordpol till sydpol.",
        "Jag kan ge exempel på ämnen som dras till magneter, till exempel järn och nickel.",
        "Jag vet att en magnet som delas blir två nya magneter med både nordpol och sydpol.",
        "Jag vet på enkel nivå vad som gör ett ämne magnetiskt.",
        "Jag vet att magnetism kan förstöras om man värmer en magnet eller slår hårt på den."
      ]
    },
    {
      "title": "6. Elektromagnetism och elektromagneter",
      "items": [
        "Jag vet att elektrisk ström i en ledning skapar ett magnetfält.",
        "Jag vet att Ørsted upptäckte att el och magnetism hänger ihop.",
        "Jag vet att en spole ger ett tydligare magnetfält än en rak ledning.",
        "Jag vet vad en elektromagnet är.",
        "Jag vet att en elektromagnet består av en spole och ofta en järnkärna.",
        "Jag vet hur man kan göra en elektromagnet starkare.",
        "Jag vet att elektromagneten bara fungerar när strömmen är på.",
        "Jag kan ge exempel på hur elektromagneter används, till exempel i skrotkranar."
      ]
    },
    {
      "title": "7. Motorer, generatorer och induktion",
      "items": [
        "Jag vet att en elmotor omvandlar elektrisk ström till rörelse.",
        "Jag vet att en generator omvandlar rörelse till elektrisk ström.",
        "Jag vet att Faraday visade att magnetism kan skapa elektrisk ström.",
        "Jag vet vad induktion betyder: att ett förändrat magnetfält kan skapa ström.",
        "Jag vet att det krävs rörelse mellan magnet och spole för att induktion ska uppstå.",
        "Jag vet att induktionsströmmen blir större om magneten är starkare eller rör sig snabbare.",
        "Jag vet att induktionsströmmen också ökar om spolen har fler varv.",
        "Jag kan förklara sambandet mellan magnet, spole och generator på enkel nivå."
      ]
    },
    {
      "title": "8. Transformatorn",
      "items": [
        "Jag vet att en transformator används för att höja eller sänka spänningen.",
        "Jag vet att en transformator består av två spolar och en järnkärna.",
        "Jag vet att den ena spolen skapar ett varierande magnetfält och att den andra får en inducerad spänning.",
        "Jag vet att en transformator fungerar med växelström, inte med vanlig likström.",
        "Jag vet att mobilens laddare behöver sänka vägguttagets höga spänning."
      ]
    },
    {
      "title": "9. Ohms lag och beräkningar",
      "items": [
        "Jag vet att U står för spänning, I för strömstyrka och R för resistans.",
        "Jag kan skriva Ohms lag: U = R · I.",
        "Jag kan använda formeln I = U / R.",
        "Jag kan använda formeln R = U / I.",
        "Jag kan räkna ut strömstyrkan om jag vet spänning och resistans.",
        "Jag kan räkna ut resistansen om jag vet spänning och strömstyrka.",
        "Jag vet att resistansen ökar när resistorer seriekopplas.",
        "Jag vet att den totala resistansen minskar när resistorer parallellkopplas."
      ]
    },
    {
      "title": "10. Begrepp jag behöver kunna",
      "items": [
        "elektrisk ström",
        "spänning",
        "resistans",
        "resistor",
        "ledare",
        "isolator",
        "likström",
        "växelström",
        "magnet",
        "magnetfält",
        "elektromagnet",
        "elektromagnetism",
        "elektrisk motor",
        "generator",
        "induktion",
        "transformator",
        "Ohms lag"
      ]
    }
  ]
}
